nk225op.py
nk225op-0.1.9.dist-info/LICENSE
nk225op-0.1.9.dist-info/METADATA
nk225op-0.1.9.dist-info/WHEEL
nk225op-0.1.9.dist-info/top_level.txt
nk225op-0.1.9.dist-info/RECORD
