Metadata-Version: 2.1
Name: nk225op
Version: 0.1.9
Summary: Download latest Option Price(nk255) from JPX
Home-page: https://github.com/zaq9/nk225op
Author: zaq
Author-email: zaq_9@yahoo.co.jp
License: UNKNOWN
Keywords: options,python,finance
Platform: UNKNOWN
Classifier: Development Status :: 3 - Alpha
Classifier: Programming Language :: Python :: 3
Requires-Dist: pandas
Requires-Dist: bs4
